[
    {
        "name": "Employee 1",
        "age": null,
        "salary": 2900
    },
    {
        "name": "Employee 2",
        "age": 37,
        "salary": 3100
    },
    {
        "name": "Employee 3",
        "age": "22",
        "salary": 2100
    },
    {
        "name": "Employee 4",
        "age": 50,
        "salary": 4700
    },
    {
        "name": "Employee 5",
        "age": 48,
        "salary": 3600
    },
    {
        "name": "Employee 6",
        "age": "44",
        "salary": 3400
    },
    {
        "name": "Employee 7",
        "age": 56,
        "salary": 5000
    },
    {
        "name": "Employee 8",
        "age": 26,
        "salary": 1800
    },
    {
        "name": "Employee 9",
        "age": 61,
        "salary": 6000
    },
    {
        "name": "Employee 10",
        "salary": [
            5800
        ]
    }
]